hugo-0.153.0.dist-info/WHEEL
hugo-0.153.0.dist-info/entry_points.txt
hugo-0.153.0.dist-info/top_level.txt
hugo-0.153.0.dist-info/METADATA
hugo-0.153.0.dist-info/RECORD
hugo-0.153.0.dist-info/licenses/LICENSE-hugo.txt
hugo-0.153.0.dist-info/licenses/LICENSE
hugo/cli.py
hugo/__main__.py
hugo/binaries/.gitignore
hugo/binaries/hugo-0.153.0-linux-ppc64le
