Metadata-Version: 2.4
Name: hugo
Version: 0.153.0
Summary: Binaries for the 'extended + withdeploy' edition of the Hugo static site generator, installable with pip
Author-email: Agriya Khetarpal <agriyakhetarpal@outlook.com>
Maintainer-email: Agriya Khetarpal <agriyakhetarpal@outlook.com>
License-Expression: Apache-2.0
Project-URL: Homepage, https://github.com/agriyakhetarpal/hugo-python-distributions
Project-URL: Issues, https://github.com/agriyakhetarpal/hugo-python-distributions/issues
Project-URL: Changelog, https://github.com/agriyakhetarpal/hugo-python-distributions/releases
Classifier: Development Status :: 3 - Alpha
Classifier: Intended Audience :: Developers
Classifier: Intended Audience :: Information Technology
Classifier: Operating System :: Unix
Classifier: Operating System :: MacOS
Classifier: Operating System :: Microsoft :: Windows
Classifier: Programming Language :: Go
Classifier: Programming Language :: Zig
Classifier: Programming Language :: Python
Classifier: Programming Language :: Python :: 3
Classifier: Programming Language :: Python :: 3 :: Only
Classifier: Programming Language :: Python :: 3.10
Classifier: Programming Language :: Python :: 3.11
Classifier: Programming Language :: Python :: 3.12
Classifier: Programming Language :: Python :: 3.13
Classifier: Programming Language :: Python :: 3.14
Classifier: Topic :: Internet
Classifier: Topic :: Internet :: WWW/HTTP :: Dynamic Content :: Content Management System
Classifier: Topic :: Internet :: WWW/HTTP :: Browsers
Classifier: Topic :: Utilities
Requires-Python: >=3.10
License-File: LICENSE
License-File: LICENSE-hugo.txt
Dynamic: license-file
